grpc_cache/__init__.py
grpc_cache/asyncio.py
grpc_cache/backends/__init__.py
grpc_cache/backends/inmemory.py
grpc_cache/backends/redis.py
grpc_cache/cache.py
grpc_cache/exceptions.py
grpc_cache/types.py
grpc_cache-0.1.5.dist-info/LICENSE
grpc_cache-0.1.5.dist-info/METADATA
grpc_cache-0.1.5.dist-info/WHEEL
grpc_cache-0.1.5.dist-info/RECORD
